log_request_id/__init__.py
log_request_id/filters.py
log_request_id/middleware.py
log_request_id/models.py
log_request_id/session.py
log_request_id/tests.py
log_request_id/__pycache__/__init__.cpython-38.pyc
log_request_id/__pycache__/middleware.cpython-38.pyc
context_vars_log_request_id-1.0.1.dist-info/LICENSE
context_vars_log_request_id-1.0.1.dist-info/METADATA
context_vars_log_request_id-1.0.1.dist-info/WHEEL
context_vars_log_request_id-1.0.1.dist-info/top_level.txt
context_vars_log_request_id-1.0.1.dist-info/RECORD
