Metadata-Version: 2.1
Name: context-vars-log-request-id
Version: 1.0.1
Summary: Django/Daphne middleware and log filter to attach a unique ID to every log message generated as part of a request using contextvars
Home-page: UNKNOWN
Author: Aryan Kapoor
Author-email: pro.akapoor@gmail.com
License: BSD
Platform: UNKNOWN
License-File: LICENSE
Requires-Dist: django (>=1.8)
